{"present": {"1 Singular": {"Affirmative": "scairdim", "Question": "an scairdim?", "Negative": "n\u00ed scairdim"}, "2 Singular": {"Affirmative": "scairdeann t\u00fa", "Question": "an scairdeann t\u00fa?", "Negative": "n\u00ed scairdeann t\u00fa"}, "3 Singular": {"Male": {"Affirmative": "scairdeann s\u00e9", "Question": "an scairdeann s\u00e9?", "Negative": "n\u00ed scairdeann s\u00e9"}, "Female": {"Affirmative": "scairdeann s\u00ed", "Question": "an scairdeann s\u00ed?", "Negative": "n\u00ed scairdeann s\u00ed"}}, "1 Plural": {"Compressed": {"Affirmative": "scairdimid", "Question": "an scairdimid?", "Negative": "n\u00ed scairdimid"}, "Extended": {"Affirmative": "scairdeann muid", "Question": "an scairdeann muid?", "Negative": "n\u00ed scairdeann muid"}}, "2 Plural": {"Affirmative": "scairdeann sibh", "Question": "an scairdeann sibh?", "Negative": "n\u00ed scairdeann sibh"}, "3 Plural": {"Affirmative": "scairdeann siad", "Question": "an scairdeann siad?", "Negative": "n\u00ed scairdeann siad"}, "Passive": {"Affirmative": "scairdtear", "Question": "an scairdtear?", "Negative": "n\u00ed scairdtear"}}, "future": {"1 Singular": {"Affirmative": "scairdfidh m\u00e9", "Question": "an scairdfidh m\u00e9?", "Negative": "n\u00ed scairdfidh m\u00e9"}, "2 Singular": {"Affirmative": "scairdfidh t\u00fa", "Question": "an scairdfidh t\u00fa?", "Negative": "n\u00ed scairdfidh t\u00fa"}, "3 Singular": {"Male": {"Affirmative": "scairdfidh s\u00e9", "Question": "an scairdfidh s\u00e9?", "Negative": "n\u00ed scairdfidh s\u00e9"}, "Female": {"Affirmative": "scairdfidh s\u00ed", "Question": "an scairdfidh s\u00ed?", "Negative": "n\u00ed scairdfidh s\u00ed"}}, "1 Plural": {"Compressed": {"Affirmative": "scairdfimid", "Question": "an scairdfimid?", "Negative": "n\u00ed scairdfimid"}, "Extended": {"Affirmative": "scairdfidh muid", "Question": "an scairdfidh muid?", "Negative": "n\u00ed scairdfidh muid"}}, "2 Plural": {"Affirmative": "scairdfidh sibh", "Question": "an scairdfidh sibh?", "Negative": "n\u00ed scairdfidh sibh"}, "3 Plural": {"Affirmative": "scairdfidh siad", "Question": "an scairdfidh siad?", "Negative": "n\u00ed scairdfidh siad"}, "Passive": {"Affirmative": "scairdfear", "Question": "an scairdfear?", "Negative": "n\u00ed scairdfear"}}, "past": {"1 Singular": {"Affirmative": "scaird m\u00e9", "Question": "ar scaird m\u00e9?", "Negative": "n\u00edor scaird m\u00e9"}, "2 Singular": {"Affirmative": "scaird t\u00fa", "Question": "ar scaird t\u00fa?", "Negative": "n\u00edor scaird t\u00fa"}, "3 Singular": {"Male": {"Affirmative": "scaird s\u00e9", "Question": "ar scaird s\u00e9?", "Negative": "n\u00edor scaird s\u00e9"}, "Female": {"Affirmative": "scaird s\u00ed", "Question": "ar scaird s\u00ed?", "Negative": "n\u00edor scaird s\u00ed"}}, "1 Plural": {"Compressed": {"Affirmative": "scairdeamar", "Question": "ar scairdeamar?", "Negative": "n\u00edor scairdeamar"}, "Extended": {"Affirmative": "scaird muid", "Question": "ar scaird muid?", "Negative": "n\u00edor scaird muid"}}, "2 Plural": {"Affirmative": "scaird sibh", "Question": "ar scaird sibh?", "Negative": "n\u00edor scaird sibh"}, "3 Plural": {"Compressed": {"Affirmative": "scaird siad", "Question": "ar scaird siad?", "Negative": "n\u00edor scaird siad"}, "Extended": {"Affirmative": "scairdeadar", "Question": "ar scairdeadar?", "Negative": "n\u00edor scairdeadar"}}, "Passive": {"Affirmative": "scairdeadh", "Question": "ar scairdeadh?", "Negative": "n\u00edor scairdeadh"}}, "condi": {"1 Singular": {"Affirmative": "scairdfinn", "Question": "an scairdfinn?", "Negative": "n\u00ed scairdfinn"}, "2 Singular": {"Affirmative": "scairdfe\u00e1", "Question": "an scairdfe\u00e1?", "Negative": "n\u00ed scairdfe\u00e1"}, "3 Singular": {"Male": {"Affirmative": "scairdfeadh s\u00e9", "Question": "an scairdfeadh s\u00e9?", "Negative": "n\u00ed scairdfeadh s\u00e9"}, "Female": {"Affirmative": "scairdfeadh s\u00ed", "Question": "an scairdfeadh s\u00ed?", "Negative": "n\u00ed scairdfeadh s\u00ed"}}, "1 Plural": {"Compressed": {"Affirmative": "scairdfimis", "Question": "an scairdfimis?", "Negative": "n\u00ed scairdfimis"}, "Extended": {"Affirmative": "scairdfeadh muid", "Question": "an scairdfeadh muid?", "Negative": "n\u00ed scairdfeadh muid"}}, "2 Plural": {"Affirmative": "scairdfeadh sibh", "Question": "an scairdfeadh sibh?", "Negative": "n\u00ed scairdfeadh sibh"}, "3 Plural": {"Compressed": {"Affirmative": "scairdfid\u00eds", "Question": "an scairdfid\u00eds?", "Negative": "n\u00ed scairdfid\u00eds"}, "Extended": {"Affirmative": "scairdfeadh siad", "Question": "an scairdfeadh siad?", "Negative": "n\u00ed scairdfeadh siad"}}, "Passive": {"Affirmative": "scairdf\u00ed", "Question": "an scairdf\u00ed?", "Negative": "n\u00ed scairdf\u00ed"}}, "imper": {"1 Singular": {"Affirmative": "scairdim!", "Negative": "n\u00e1 scairdim!"}, "2 Singular": {"Affirmative": "scaird!", "Negative": "n\u00e1 scaird!"}, "3 Singular": {"Male": {"Affirmative": "scairdeadh s\u00e9!", "Negative": "n\u00e1 scairdeadh s\u00e9!"}, "Female": {"Affirmative": "scairdeadh s\u00ed!", "Negative": "n\u00e1 scairdeadh s\u00ed!"}}, "1 Plural": {"Compressed": {"Affirmative": "scairdimis!", "Negative": "n\u00e1 scairdimis!"}, "Extended": {"Affirmative": "scairdeadh muid!", "Negative": "n\u00e1 scairdeadh muid!"}}, "2 Plural": {"Affirmative": "scairdig\u00ed!", "Negative": "n\u00e1 scairdig\u00ed!"}, "3 Plural": {"Compressed": {"Affirmative": "scairdid\u00eds!", "Negative": "n\u00e1 scairdid\u00eds!"}, "Extended": {"Affirmative": "scairdeadh siad!", "Negative": "n\u00e1 scairdeadh siad!"}}, "Passive": {"Affirmative": "scairdtear!", "Negative": "n\u00e1 scairdtear!"}}, "pastConti": {"1 Singular": {"Affirmative": "scairdinn", "Question": "an scairdinn?", "Negative": "n\u00ed scairdinn"}, "2 Singular": {"Affirmative": "scairdte\u00e1", "Question": "an scairdte\u00e1?", "Negative": "n\u00ed scairdte\u00e1"}, "3 Singular": {"Male": {"Affirmative": "scairdeadh s\u00e9", "Question": "an scairdeadh s\u00e9?", "Negative": "n\u00ed scairdeadh s\u00e9"}, "Female": {"Affirmative": "scairdeadh s\u00ed", "Question": "an scairdeadh s\u00ed?", "Negative": "n\u00ed scairdeadh s\u00ed"}}, "1 Plural": {"Compressed": {"Affirmative": "scairdimis", "Question": "an scairdimis?", "Negative": "n\u00ed scairdimis"}, "Extended": {"Affirmative": "scairdeadh muid", "Question": "an scairdeadh muid?", "Negative": "n\u00ed scairdeadh muid"}}, "2 Plural": {"Affirmative": "scairdeadh sibh", "Question": "an scairdeadh sibh?", "Negative": "n\u00ed scairdeadh sibh"}, "3 Plural": {"Compressed": {"Affirmative": "scairdid\u00eds", "Question": "an scairdid\u00eds?", "Negative": "n\u00ed scairdid\u00eds"}, "Extended": {"Affirmative": "scairdeadh siad", "Question": "an scairdeadh siad?", "Negative": "n\u00ed scairdeadh siad"}}, "Passive": {"Affirmative": "scairdt\u00ed", "Question": "an scairdt\u00ed?", "Negative": "n\u00ed scairdt\u00ed"}}, "subj": {"1 Singular": {"Affirmative": "go scairde m\u00e9", "Negative": "n\u00e1r scairde m\u00e9"}, "2 Singular": {"Affirmative": "go scairde t\u00fa", "Negative": "n\u00e1r scairde t\u00fa"}, "3 Singular": {"Male": {"Affirmative": "go scairde s\u00e9", "Negative": "n\u00e1r scairde s\u00e9"}, "Female": {"Affirmative": "go scairde s\u00ed", "Negative": "n\u00e1r scairde s\u00ed"}}, "1 Plural": {"Compressed": {"Affirmative": "go scairdimid", "Negative": "n\u00e1r scairdimid"}, "Extended": {"Affirmative": "go scairde muid", "Negative": "n\u00e1r scairde muid"}}, "2 Plural": {"Affirmative": "go scairde sibh", "Negative": "n\u00e1r scairde sibh"}, "3 Plural": {"Affirmative": "go scairde siad", "Negative": "n\u00e1r scairde siad"}, "Passive": {"Affirmative": "go scairdtear", "Negative": "n\u00e1r scairdtear"}}, "verbal noun": "scairdeadh", "verbal adjective": "scairdte"}